test/model/__init__.py
test/model/eq/__init__.py
test/model/eq/all_test.py
test/model/eq/cev_test.py
test/model/eq/cevconst_test.py
test/model/eq/cevlocalvol_test.py
test/model/eq/gbm_test.py
test/model/eq/gbmconst_test.py
test/model/eq/gbmlocalvol_test.py
test/model/eq/heston_test.py
test/model/etc/__init__.py
test/model/etc/brownian_motion_test.py
test/model/etc/random_test.py
test/model/fx/__init__.py
test/model/fx/gk_test.py
test/model/ir/__init__.py
test/model/ir/bk1f_test.py
test/model/ir/cir1f_test.py
test/model/ir/cir1fext_test.py
test/model/ir/g2ext_test.py
test/model/ir/hw1f_test.py
test/model/ir/ir_cali_test.py
test/model/ir/vasicek_test.py
test/unit/__init__.py
test/unit/general_info.py
test/unit/general_info_random.py
test/unit/instrument_pricing.py
test/unit/model_martinagle.py
xenarix/__init__.py
xenarix/calculations.py
xenarix/calibration.py
xenarix/common.py
xenarix/instruments.py
xenarix/martingale.py
xenarix/mxqlib.py
xenarix/results.py
xenarix/templatebuilder.py
xenarix/utilities.py
xenarix/viewer.py
xenarix/xenarix_engine.exe
xenarix/xenarix_engine.out
xenarix/sample/__init__.py
xenarix/sample/eq.py
xenarix/sample/fx.py
xenarix/sample/ir.py
xenarix/test/__init__.py
xenarix/test/calculation.py
xenarix/test/martinagle.py
xenarix/test/option.py
xenarix-0.1.26.dist-info/LICENSE
xenarix-0.1.26.dist-info/METADATA
xenarix-0.1.26.dist-info/WHEEL
xenarix-0.1.26.dist-info/top_level.txt
xenarix-0.1.26.dist-info/RECORD
