Metadata-Version: 2.1
Name: xenarix
Version: 0.1.26
Summary: python library for xenarix
Home-page: https://github.com/minikie/xenarix
Author: montrix
Author-email: master@montrix.co.kr
License: Montrix Non-Commercial License
Keywords: scenario,finance,scenariogenerator,esg,alm
Platform: UNKNOWN
Classifier: Programming Language :: Python :: 2
Classifier: Programming Language :: Python :: 3
Requires-Dist: numpy (>=1.14.5)
Requires-Dist: matplotlib (>=2.2.2)
Requires-Dist: pandas (>=0.23.3)
Requires-Dist: scipy (>=1.2.0)
Requires-Dist: statsmodels
